MANIFEST.in
README.rst
ez_setup.py
setup.py
greencache/__init__.py
greencache/config.py
greencache/data_dir.py
greencache/file_cache.py
greencache/simple_cache.py
greencache/version.py
greencache.egg-info/PKG-INFO
greencache.egg-info/SOURCES.txt
greencache.egg-info/dependency_links.txt
greencache.egg-info/requires.txt
greencache.egg-info/top_level.txt